myst_sphinx_gallery/__init__.py
myst_sphinx_gallery/config.py
myst_sphinx_gallery/directives.py
myst_sphinx_gallery/gallery.py
myst_sphinx_gallery/grid.py
myst_sphinx_gallery/images.py
myst_sphinx_gallery/sphinx_ext.py
myst_sphinx_gallery/utils.py
myst_sphinx_gallery/_static/myst_sphinx_gallery.css
myst_sphinx_gallery/_static/no_image.png
myst_sphinx_gallery-0.3.0.dist-info/LICENSE
myst_sphinx_gallery-0.3.0.dist-info/METADATA
myst_sphinx_gallery-0.3.0.dist-info/WHEEL
myst_sphinx_gallery-0.3.0.dist-info/top_level.txt
myst_sphinx_gallery-0.3.0.dist-info/RECORD
