Metadata-Version: 2.1
Name: myst_sphinx_gallery
Version: 0.3.0
Summary: A Sphinx extension that builds galleries of examples from any set of myst-style markdown/notebook or rst files.
Author-email: "Chengyan Fan (Fancy)" <fanchengyan@outlook.com>
License: MIT License
Project-URL: Documentation, https://myst-sphinx-gallery.readthedocs.io/en/latest/
Project-URL: Source, https://github.com/Fanchengyan/myst-sphinx-gallery
Keywords: gallery,markdown,parser,jupyter,docutils,sphinx
Classifier: Development Status :: 4 - Beta
Classifier: Framework :: Sphinx :: Extension
Classifier: Intended Audience :: Developers
Classifier: Programming Language :: Python
Classifier: Programming Language :: Python :: 3 :: Only
Classifier: Programming Language :: Python :: 3.8
Classifier: Programming Language :: Python :: 3.9
Classifier: Programming Language :: Python :: 3.10
Classifier: Programming Language :: Python :: 3.11
Classifier: Programming Language :: Python :: 3.12
Classifier: Operating System :: OS Independent
Classifier: License :: OSI Approved :: MIT License
Requires-Python: >=3.8
License-File: LICENSE
Requires-Dist: pillow
Requires-Dist: myst-nb
Requires-Dist: sphinx-design
Provides-Extra: code_style
Requires-Dist: pre-commit ; extra == 'code_style'
Requires-Dist: ruff ; extra == 'code_style'
Provides-Extra: dev
Requires-Dist: pre-commit ; extra == 'dev'
Requires-Dist: ruff ; extra == 'dev'
Requires-Dist: coverage ; extra == 'dev'
Requires-Dist: pytest ; extra == 'dev'
Requires-Dist: pytest-cov ; extra == 'dev'
Requires-Dist: matplotlib ; extra == 'dev'
Requires-Dist: numpy ; extra == 'dev'
Provides-Extra: test
Requires-Dist: coverage ; extra == 'test'
Requires-Dist: pytest ; extra == 'test'
Requires-Dist: pytest-cov ; extra == 'test'
Requires-Dist: matplotlib ; extra == 'test'
Requires-Dist: numpy ; extra == 'test'
